[
  {
    "branch": "master",
    "url": "https://shayanline.github.io/Inkfall/",
    "sha": "bd92d99",
    "updated": "2026-06-29 14:36"
  },
  {
    "branch": "copilot/fix-small-text-and-huds",
    "url": "https://shayanline.github.io/Inkfall/copilot-fix-small-text-and-huds/",
    "sha": "2dd5e8f",
    "updated": "2026-06-29 14:24"
  },
  {
    "branch": "fix/web-render-lighting",
    "url": "https://shayanline.github.io/Inkfall/fix-web-render-lighting/",
    "sha": "48ce376",
    "updated": "2026-06-29 14:34"
  }
]
